skrit_r0073rr0r/__init__.py
skrit_r0073rr0r/litrovacki.py
skrit_r0073rr0r/satrovacki.py
skrit_r0073rr0r/skrit.py
skrit_r0073rr0r/utrovacki.py
skrit_r0073rr0r-0.2.6.dist-info/LICENSE
skrit_r0073rr0r-0.2.6.dist-info/METADATA
skrit_r0073rr0r-0.2.6.dist-info/WHEEL
skrit_r0073rr0r-0.2.6.dist-info/top_level.txt
skrit_r0073rr0r-0.2.6.dist-info/RECORD
