Metadata-Version: 2.1
Name: skrit-r0073rr0r
Version: 0.2.6
Summary: Python Skrit
Author-email: r0073rr0r <direktor@кгб.срб>
Project-URL: Homepage, https://github.com/r0073rr0r/PSkrit
Classifier: Programming Language :: Python :: 3
Classifier: License :: OSI Approved :: MIT License
Classifier: Operating System :: OS Independent
Requires-Python: >=3.0
License-File: LICENSE
